MANIFEST.in
requirements.txt
setup.py
bvh_converter/__init__.py
bvh_converter/__main__.py
bvh_converter/bvh.py
bvh_converter/bvhplayer_skeleton.py
bvh_converter.egg-info/PKG-INFO
bvh_converter.egg-info/SOURCES.txt
bvh_converter.egg-info/dependency_links.txt
bvh_converter.egg-info/entry_points.txt
bvh_converter.egg-info/requires.txt
bvh_converter.egg-info/top_level.txt